Test.py
mpzinke/__init__.py
mpzinke/DownloadIterator/DownloadIterator.py
mpzinke/DownloadIterator/__init__.py
mpzinke/Generic/Generic.py
mpzinke/Generic/__init__.py
mpzinke/Generic/__main__.py
mpzinke/IsJSON/IsJSON.py
mpzinke/IsJSON/__init__.py
mpzinke/Server/Route.py
mpzinke/Server/Server.py
mpzinke/Server/__init__.py
mpzinke/threading/BaseThread.py
mpzinke/threading/DelayThread.py
mpzinke/threading/LoopingThread.py
mpzinke/threading/__init__.py
mpzinke-0.53.dist-info/LICENSE
mpzinke-0.53.dist-info/METADATA
mpzinke-0.53.dist-info/WHEEL
mpzinke-0.53.dist-info/top_level.txt
mpzinke-0.53.dist-info/RECORD
