Metadata-Version: 2.1
Name: mpzinke
Version: 0.53
Summary: Python libraries for MPZinke.
Author: Mathew Zinke
Project-URL: Homepage, https://github.com/MPZinke/Python
Project-URL: Bug Tracker, https://github.com/MPZinke/Python/issues
Classifier: Programming Language :: Python :: 3
Classifier: License :: OSI Approved :: GNU General Public License v3 (GPLv3)
Classifier: Operating System :: OS Independent
Requires-Python: >=3.11
License-File: LICENSE
